README.md
setup.cfg
setup.py
artan.egg-info/PKG-INFO
artan.egg-info/SOURCES.txt
artan.egg-info/dependency_links.txt
artan.egg-info/not-zip-safe
artan.egg-info/top_level.txt
python/artan/__init__.py
python/artan/spark_functions.py
python/artan/utils.py
python/artan/filter/__init__.py
python/artan/filter/filter_params.py
python/artan/filter/least_mean_squares_filter.py
python/artan/filter/linear_kalman_filter.py
python/artan/filter/recursive_least_squares_filter.py
python/artan/smoother/__init__.py
python/artan/smoother/linear_kalman_smoother.py
python/artan/state/__init__.py
python/artan/state/stateful_transformer.py