Metadata-Version: 2.1
Name: artan
Version: 0.5.1
Summary: Online latent state estimation with Apache Spark.
Home-page: https://github.com/ozancicek/artan
Author: Ozan Cicekci
Author-email: ozancancicekci@gmail.com
License: http://www.apache.org/licenses/LICENSE-2.0
Keywords: pyspark,kalman,filter,sparkml,structured,streaming
Platform: UNKNOWN
Classifier: Development Status :: 3 - Alpha
Classifier: License :: OSI Approved :: Apache Software License
Classifier: Programming Language :: Python :: 3.6
Requires-Python: >=3.6
